<Root>
<Comments>
<c f="1" b="1" e="1"/>
<c f="1" b="2" e="2"/>
<c f="1" b="3" e="3"/>
<c f="1" b="4" e="4"/>
<c f="1" b="5" e="5"/>
<c f="1" b="6" e="6"/>
<c f="1" b="7" e="7"/>
<c f="1" b="8" e="8"/>
<c f="1" b="9" e="9"/>
<c f="1" b="10" e="10"/>
<c f="1" b="11" e="11"/>
<c f="1" b="12" e="12"/>
<c f="1" b="14" e="12"/>
</Comments>
<Macros/>
<Comments>
<c f="2" b="1" e="1"/>
<c f="2" b="2" e="2"/>
<c f="2" b="3" e="3"/>
<c f="2" b="4" e="4"/>
<c f="2" b="5" e="5"/>
<c f="2" b="6" e="6"/>
<c f="2" b="7" e="7"/>
<c f="2" b="8" e="8"/>
<c f="2" b="9" e="9"/>
<c f="2" b="10" e="10"/>
<c f="2" b="11" e="11"/>
<c f="2" b="12" e="12"/>
<c f="2" b="14" e="12"/>
<c f="2" b="28" e="28"/>
<c f="2" b="30" e="28"/>
</Comments>
<Macros/>
<tun>
<ns name="llvm" id="9463627ef3a50bec46cd15737993577a_544dadc8774ac7e8cdf9804c9bca3e1f" file="2" linestart="19" lineend="28" original="">
<cr namespace="llvm" access="none" kind="class" name="StringRef" id="9463627ef3a50bec46cd15737993577a_1025e290e4030296f4991e57e4952f33" file="2" linestart="20" lineend="20" previous="6f9d54688deb2fea7e6a760a21186275_1025e290e4030296f4991e57e4952f33"/>
<cr namespace="llvm" access="none" depth="2" kind="class" name="MSP430MCAsmInfo" id="9463627ef3a50bec46cd15737993577a_e8afcc97e4b9b6bc9e4770410fb85ff5" file="2" linestart="22" lineend="26">
<base access="public">
<rt>
<cr id="f78cfd7ef40477bc4cfcf388a4e09d63_20e78ca3a5bb5c7726ce6d6527fcde59"/>
</rt>
</base>
<cr access="public" kind="class" name="MSP430MCAsmInfo" id="9463627ef3a50bec46cd15737993577a_3fc47f1a8a65ea60b78b96e6fa97678a" file="2" linestart="22" lineend="22"/>
<m name="anchor" id="9463627ef3a50bec46cd15737993577a_d3d124859759a0f46bd4036c6f2642ef" file="2" linestart="23" lineend="23" access="private" hasbody="true">
<fpt proto="void">
<bt name="void"/>
</fpt>
</m>
<Decl access="public"/>
<c name="MSP430MCAsmInfo" id="9463627ef3a50bec46cd15737993577a_60d3b3d70aabc6120de50bc3156c1ddf" file="2" linestart="25" lineend="25" explicit="true" access="public" hasbody="true">
<fpt proto="void">
<bt name="void"/>
</fpt>
<p name="TT" proto="llvm::StringRef" access2="none">
<rt>
<cr id="6f9d54688deb2fea7e6a760a21186275_1025e290e4030296f4991e57e4952f33"/>
</rt>
<Stmt>

</Stmt>
</p>
</c>
<m name="operator=" id="9463627ef3a50bec46cd15737993577a_79a353b1fb5709188b90b430542ca960" file="2" linestart="22" implicit="true" operator="true" access="public" inline="true">
<fpt proto="llvm::MSP430MCAsmInfo &amp;">
<lrf>
<rt>
<cr id="9463627ef3a50bec46cd15737993577a_e8afcc97e4b9b6bc9e4770410fb85ff5"/>
</rt>
</lrf>
</fpt>
<p name="" proto="const llvm::MSP430MCAsmInfo &amp;" isRef="true" isLiteral="true" access2="none">
<lrf>
<QualType const="true">
<rt>
<cr id="9463627ef3a50bec46cd15737993577a_e8afcc97e4b9b6bc9e4770410fb85ff5"/>
</rt>
</QualType>
</lrf>
<Stmt>

</Stmt>
</p>
</m>
<d name="~MSP430MCAsmInfo" id="9463627ef3a50bec46cd15737993577a_ede2ba5ac0206cbd3a6fe20885c6dc16" file="2" linestart="22" lineend="22" implicit="true" access="public" inline="true" hasbody="true" isdef="true">
<fpt proto="void">
<bt name="void"/>
<exception_specifiers nothrow="true"/>
</fpt>
<Stmt>
<u lb="22" cb="9"/>

</Stmt>
</d>
<c name="MSP430MCAsmInfo" id="9463627ef3a50bec46cd15737993577a_e18293a9833584f2fa7277b9c963b162" file="2" linestart="22" lineend="22" copyconst="true" implicit="true" access="public" inline="true">
<fpt proto="void">
<bt name="void"/>
</fpt>
<p name="" proto="const llvm::MSP430MCAsmInfo &amp;" isRef="true" isLiteral="true" access2="none">
<lrf>
<QualType const="true">
<rt>
<cr id="9463627ef3a50bec46cd15737993577a_e8afcc97e4b9b6bc9e4770410fb85ff5"/>
</rt>
</QualType>
</lrf>
<Stmt>

</Stmt>
</p>
</c>
</cr>
</ns>
<NamedDecl name="&lt;using-directive&gt;" id="5b3c042951b515b92b2f8df96340a558_6728b6b0f829183eb7bbd3d3d987c87d" file="1" linestart="16" lineend="16"/>
<m name="anchor" id="5b3c042951b515b92b2f8df96340a558_d3d124859759a0f46bd4036c6f2642ef" file="1" linestart="18" lineend="18" previous="9463627ef3a50bec46cd15737993577a_d3d124859759a0f46bd4036c6f2642ef" access="private" hasbody="true" isdef="true">
<fpt proto="void">
<bt name="void"/>
</fpt>
<Stmt>
<u lb="18" cb="32" le="18" ce="34"/>

</Stmt>
</m>
<c name="MSP430MCAsmInfo" id="5b3c042951b515b92b2f8df96340a558_60d3b3d70aabc6120de50bc3156c1ddf" file="1" linestart="20" lineend="27" previous="9463627ef3a50bec46cd15737993577a_60d3b3d70aabc6120de50bc3156c1ddf" explicit="true" access="public" hasbody="true" isdef="true">
<fpt proto="void">
<bt name="void"/>
</fpt>
<p name="TT" proto="llvm::StringRef" access2="none">
<rt>
<cr id="6f9d54688deb2fea7e6a760a21186275_1025e290e4030296f4991e57e4952f33"/>
</rt>
<Stmt>

</Stmt>
</p>
<BaseInit>
<n10 lb="20" cb="18">
<typeptr id="f78cfd7ef40477bc4cfcf388a4e09d63_5f71cb8c8b81f9da8ff354f6c0dc0a11"/>
<temp/>
</n10>

</BaseInit>
<Stmt>
<u lb="20" cb="48" le="27" ce="1">
<xop lb="21" cb="3" le="21" ce="43" kind="=">
<mex lb="21" cb="3" kind="lvalue" id="b2b9336dfe6b80bb5834e13979c78f51_7956651dbcb73a6035f581fd867b78bd" nm="PointerSize" arrow="1">
<n32 lb="21" cb="3">
<n19 lb="21" cb="3"/>
</n32>
</mex>
<n32 lb="21" cb="17" le="21" ce="43">
<xop lb="21" cb="17" le="21" ce="43" kind="=">
<mex lb="21" cb="17" kind="lvalue" id="b2b9336dfe6b80bb5834e13979c78f51_7774f3a0ea64078210ad7f0f1b05e3f2" nm="CalleeSaveStackSlotSize" arrow="1">
<n32 lb="21" cb="17">
<n19 lb="21" cb="17"/>
</n32>
</mex>
<n32 lb="21" cb="43">
<n45 lb="21" cb="43">
<flit/>
</n45>
</n32>
</xop>
</n32>
</xop>
<xop lb="23" cb="3" le="23" ce="19" kind="=">
<mex lb="23" cb="3" kind="lvalue" id="b2b9336dfe6b80bb5834e13979c78f51_b454cd304af0749db1b733b37d4ac810" nm="CommentString" arrow="1">
<n32 lb="23" cb="3">
<n19 lb="23" cb="3"/>
</n32>
</mex>
<n32 lb="23" cb="19">
<n52 lb="23" cb="19">
<slit/>
</n52>
</n32>
</xop>
<xop lb="25" cb="3" le="25" ce="24" kind="=">
<mex lb="25" cb="3" kind="lvalue" id="b2b9336dfe6b80bb5834e13979c78f51_e47803b76500f7ea73e5f8298f917bb0" nm="AlignmentIsInBytes" arrow="1">
<n32 lb="25" cb="3">
<n19 lb="25" cb="3"/>
</n32>
</mex>
<n9 lb="25" cb="24"/>
</xop>
<xop lb="26" cb="3" le="26" ce="35" kind="=">
<mex lb="26" cb="3" kind="lvalue" id="b2b9336dfe6b80bb5834e13979c78f51_9fe111f85626d27359428dc6c2727999" nm="UsesELFSectionDirectiveForBSS" arrow="1">
<n32 lb="26" cb="3">
<n19 lb="26" cb="3"/>
</n32>
</mex>
<n9 lb="26" cb="35"/>
</xop>
</u>

</Stmt>
</c>
</tun>
</Root>
