<Index><File path="C:\Users\lacti\Desktop\llvm\lib\Support\Signals.cpp" id="1" stamp="1406279337"  exclude="false"/><File path="C:\Users\lacti\Desktop\llvm\include\llvm\Support\Signals.h" id="22" stamp="1406279565"  exclude="false"/><File path="C:\Users\lacti\Desktop\llvm\include\llvm\Support\Path.h" id="23" stamp="1406279565"  exclude="false"/><File path="C:\Users\lacti\Desktop\llvm\include\llvm\ADT\SmallString.h" id="24" stamp="1406279562"  exclude="false"/><File path="C:\Users\lacti\Desktop\llvm\include\llvm\ADT\SmallVector.h" id="25" stamp="1406279562"  exclude="false"/><File path="C:\Users\lacti\Desktop\llvm\include\llvm\ADT\iterator_range.h" id="26" stamp="1406279562"  exclude="false"/><File path="c:\program files (x86)\microsoft visual studio 12.0\vc\include\utility" id="5" stamp="1374456138"  exclude="false"/><File path="c:\program files (x86)\microsoft visual studio 12.0\vc\include\xstddef" id="27" stamp="1374456138"  exclude="false"/><File path="c:\program files (x86)\microsoft visual studio 12.0\vc\include\stdlib.h" id="14" stamp="1374453976"  exclude="false"/><File path="c:\program files (x86)\microsoft visual studio 12.0\vc\include\crtdefs.h" id="28" stamp="1374456134"  exclude="false"/><File path="c:\program files (x86)\microsoft visual studio 12.0\vc\include\sal.h" id="29" stamp="1374456134"  exclude="false"/><File path="c:\program files (x86)\microsoft visual studio 12.0\vc\include\ConcurrencySal.h" id="30" stamp="1374453976"  exclude="false"/><File path="c:\program files (x86)\microsoft visual studio 12.0\vc\include\vadefs.h" id="31" stamp="1374456134"  exclude="false"/><File path="c:\program files (x86)\microsoft visual studio 12.0\vc\include\limits.h" id="32" stamp="1374456134"  exclude="false"/><File path="c:\program files (x86)\microsoft visual studio 12.0\vc\include\cstddef" id="33" stamp="1374456136"  exclude="false"/><File path="c:\program files (x86)\microsoft visual studio 12.0\vc\include\yvals.h" id="34" stamp="1374770146"  exclude="false"/><File path="c:\program files (x86)\microsoft visual studio 12.0\vc\include\xkeycheck.h" id="35" stamp="1374453976"  exclude="false"/><File path="c:\program files (x86)\microsoft visual studio 12.0\vc\include\use_ansi.h" id="36" stamp="1379539080"  exclude="false"/><File path="c:\program files (x86)\microsoft visual studio 12.0\vc\include\stddef.h" id="37" stamp="1374453976"  exclude="false"/><File path="c:\program files (x86)\microsoft visual studio 12.0\vc\include\initializer_list" id="38" stamp="1374456136"  exclude="false"/><File path="c:\program files (x86)\microsoft visual studio 12.0\vc\include\xtr1common" id="39" stamp="1374456138"  exclude="false"/><File path="c:\program files (x86)\microsoft visual studio 12.0\vc\include\iosfwd" id="4" stamp="1374456136"  exclude="false"/><File path="c:\program files (x86)\microsoft visual studio 12.0\vc\include\cstdio" id="40" stamp="1375394290"  exclude="false"/><File path="c:\program files (x86)\microsoft visual studio 12.0\vc\include\stdio.h" id="3" stamp="1374453976"  exclude="false"/><File path="c:\program files (x86)\microsoft visual studio 12.0\vc\include\swprintf.inl" id="41" stamp="1374770146"  exclude="false"/><File path="c:\program files (x86)\microsoft visual studio 12.0\vc\include\cstring" id="42" stamp="1375394290"  exclude="false"/><File path="c:\program files (x86)\microsoft visual studio 12.0\vc\include\string.h" id="15" stamp="1374453976"  exclude="false"/><File path="c:\program files (x86)\microsoft visual studio 12.0\vc\include\cwchar" id="43" stamp="1375394290"  exclude="false"/><File path="c:\program files (x86)\microsoft visual studio 12.0\vc\include\wchar.h" id="44" stamp="1374770146"  exclude="false"/><File path="c:\program files (x86)\microsoft visual studio 12.0\vc\include\wtime.inl" id="45" stamp="1374456134"  exclude="false"/><File path="c:\program files (x86)\microsoft visual studio 12.0\vc\include\crtdbg.h" id="16" stamp="1374456134"  exclude="false"/><File path="c:\program files (x86)\microsoft visual studio 12.0\vc\include\type_traits" id="46" stamp="1374770146"  exclude="false"/><File path="c:\program files (x86)\microsoft visual studio 12.0\vc\include\xrefwrap" id="47" stamp="1374770146"  exclude="false"/><File path="C:\Users\lacti\Desktop\llvm\include\llvm\Support\AlignOf.h" id="48" stamp="1406279565"  exclude="false"/><File path="C:\Users\lacti\Desktop\llvm\include\llvm\Support\Compiler.h" id="49" stamp="1406279565"  exclude="false"/><File path="C:\Users\lacti\Desktop\llvm\include\llvm\Config\llvm-config.h" id="50" stamp="1406282460"  exclude="false"/><File path="C:\Users\lacti\Desktop\llvm\include\llvm\Support\MathExtras.h" id="51" stamp="1406279565"  exclude="false"/><File path="C:\Users\lacti\Desktop\llvm\include\llvm\Support\SwapByteOrder.h" id="52" stamp="1406279565"  exclude="false"/><File path="C:\Users\lacti\Desktop\llvm\include\llvm\Support\DataTypes.h" id="53" stamp="1406282460"  exclude="false"/><File path="c:\program files (x86)\microsoft visual studio 12.0\vc\include\cmath" id="54" stamp="1375394290"  exclude="false"/><File path="c:\program files (x86)\microsoft visual studio 12.0\vc\include\math.h" id="55" stamp="1379539080"  exclude="false"/><File path="c:\program files (x86)\microsoft visual studio 12.0\vc\include\xtgmath.h" id="56" stamp="1379539080"  exclude="false"/><File path="c:\program files (x86)\microsoft visual studio 12.0\vc\include\inttypes.h" id="57" stamp="1374770146"  exclude="false"/><File path="c:\program files (x86)\microsoft visual studio 12.0\vc\include\stdint.h" id="58" stamp="1374456136"  exclude="false"/><File path="c:\program files (x86)\microsoft visual studio 12.0\vc\include\sys\types.h" id="59" stamp="1374453976"  exclude="false"/><File path="c:\program files (x86)\microsoft visual studio 12.0\vc\include\limits" id="60" stamp="1374456136"  exclude="false"/><File path="c:\program files (x86)\microsoft visual studio 12.0\vc\include\ymath.h" id="61" stamp="1374453976"  exclude="false"/><File path="c:\program files (x86)\microsoft visual studio 12.0\vc\include\cfloat" id="62" stamp="1374456136"  exclude="false"/><File path="c:\program files (x86)\microsoft visual studio 12.0\vc\include\float.h" id="63" stamp="1374453976"  exclude="false"/><File path="c:\program files (x86)\microsoft visual studio 12.0\vc\include\crtwrn.h" id="64" stamp="1374456134"  exclude="false"/><File path="c:\program files (x86)\microsoft visual studio 12.0\vc\include\climits" id="65" stamp="1374453976"  exclude="false"/><File path="c:\program files (x86)\microsoft visual studio 12.0\vc\include\cassert" id="66" stamp="1374456136"  exclude="false"/><File path="c:\program files (x86)\microsoft visual studio 12.0\vc\include\assert.h" id="67" stamp="1374456134"  exclude="false"/><File path="c:\program files (x86)\microsoft visual studio 12.0\vc\include\intrin.h" id="68" stamp="1379539080"  exclude="false"/><File path="c:\program files (x86)\microsoft visual studio 12.0\vc\include\setjmp.h" id="69" stamp="1374456134"  exclude="false"/><File path="c:\program files (x86)\microsoft visual studio 12.0\vc\include\immintrin.h" id="70" stamp="1374456134"  exclude="false"/><File path="c:\program files (x86)\microsoft visual studio 12.0\vc\include\wmmintrin.h" id="71" stamp="1374456134"  exclude="false"/><File path="c:\program files (x86)\microsoft visual studio 12.0\vc\include\nmmintrin.h" id="72" stamp="1374456134"  exclude="false"/><File path="c:\program files (x86)\microsoft visual studio 12.0\vc\include\smmintrin.h" id="73" stamp="1374456134"  exclude="false"/><File path="c:\program files (x86)\microsoft visual studio 12.0\vc\include\tmmintrin.h" id="74" stamp="1374456134"  exclude="false"/><File path="c:\program files (x86)\microsoft visual studio 12.0\vc\include\pmmintrin.h" id="75" stamp="1374456134"  exclude="false"/><File path="c:\program files (x86)\microsoft visual studio 12.0\vc\include\emmintrin.h" id="76" stamp="1374456134"  exclude="false"/><File path="c:\program files (x86)\microsoft visual studio 12.0\vc\include\xmmintrin.h" id="77" stamp="1374453976"  exclude="false"/><File path="c:\program files (x86)\microsoft visual studio 12.0\vc\include\mmintrin.h" id="78" stamp="1374456134"  exclude="false"/><File path="c:\program files (x86)\microsoft visual studio 12.0\vc\include\malloc.h" id="79" stamp="1374456134"  exclude="false"/><File path="c:\program files (x86)\microsoft visual studio 12.0\vc\include\ammintrin.h" id="80" stamp="1374456134"  exclude="false"/><File path="c:\program files (x86)\microsoft visual studio 12.0\vc\include\mm3dnow.h" id="81" stamp="1374456134"  exclude="false"/><File path="C:\Users\lacti\Desktop\llvm\include\llvm\Support\type_traits.h" id="82" stamp="1406279565"  exclude="false"/><File path="c:\program files (x86)\microsoft visual studio 12.0\vc\include\algorithm" id="83" stamp="1374456138"  exclude="false"/><File path="c:\program files (x86)\microsoft visual studio 12.0\vc\include\xmemory" id="84" stamp="1374453976"  exclude="false"/><File path="c:\program files (x86)\microsoft visual studio 12.0\vc\include\xmemory0" id="8" stamp="1374770146"  exclude="false"/><File path="c:\program files (x86)\microsoft visual studio 12.0\vc\include\cstdlib" id="85" stamp="1375394290"  exclude="false"/><File path="c:\program files (x86)\microsoft visual studio 12.0\vc\include\new" id="86" stamp="1374456136"  exclude="false"/><File path="c:\program files (x86)\microsoft visual studio 12.0\vc\include\exception" id="87" stamp="1374456136"  exclude="false"/><File path="c:\program files (x86)\microsoft visual studio 12.0\vc\include\xutility" id="7" stamp="1374770146"  exclude="false"/><File path="c:\program files (x86)\microsoft visual studio 12.0\vc\include\xatomic0.h" id="88" stamp="1374456138"  exclude="false"/><File path="c:\program files (x86)\microsoft visual studio 12.0\vc\include\iterator" id="89" stamp="1374456136"  exclude="false"/><File path="c:\program files (x86)\microsoft visual studio 12.0\vc\include\istream" id="90" stamp="1374770146"  exclude="false"/><File path="c:\program files (x86)\microsoft visual studio 12.0\vc\include\ostream" id="91" stamp="1374770146"  exclude="false"/><File path="c:\program files (x86)\microsoft visual studio 12.0\vc\include\ios" id="92" stamp="1374770146"  exclude="false"/><File path="c:\program files (x86)\microsoft visual studio 12.0\vc\include\xlocnum" id="93" stamp="1374453976"  exclude="false"/><File path="c:\program files (x86)\microsoft visual studio 12.0\vc\include\streambuf" id="94" stamp="1374456136"  exclude="false"/><File path="c:\program files (x86)\microsoft visual studio 12.0\vc\include\xiosbase" id="95" stamp="1374770146"  exclude="false"/><File path="c:\program files (x86)\microsoft visual studio 12.0\vc\include\xlocale" id="96" stamp="1374770146"  exclude="false"/><File path="c:\program files (x86)\microsoft visual studio 12.0\vc\include\stdexcept" id="97" stamp="1374456136"  exclude="false"/><File path="c:\program files (x86)\microsoft visual studio 12.0\vc\include\xstring" id="9" stamp="1374456138"  exclude="false"/><File path="c:\program files (x86)\microsoft visual studio 12.0\vc\include\typeinfo" id="98" stamp="1374770146"  exclude="false"/><File path="c:\program files (x86)\microsoft visual studio 12.0\vc\include\xlocinfo" id="99" stamp="1374770146"  exclude="false"/><File path="c:\program files (x86)\microsoft visual studio 12.0\vc\include\xlocinfo.h" id="100" stamp="1374453976"  exclude="false"/><File path="c:\program files (x86)\microsoft visual studio 12.0\vc\include\ctype.h" id="101" stamp="1374456134"  exclude="false"/><File path="c:\program files (x86)\microsoft visual studio 12.0\vc\include\locale.h" id="102" stamp="1374456134"  exclude="false"/><File path="c:\program files (x86)\microsoft visual studio 12.0\vc\include\xdebug" id="103" stamp="1374456138"  exclude="false"/><File path="c:\program files (x86)\microsoft visual studio 12.0\vc\include\xfacet" id="104" stamp="1374453976"  exclude="false"/><File path="c:\program files (x86)\microsoft visual studio 12.0\vc\include\system_error" id="105" stamp="1374770146"  exclude="false"/><File path="c:\program files (x86)\microsoft visual studio 12.0\vc\include\cerrno" id="106" stamp="1374456136"  exclude="false"/><File path="c:\program files (x86)\microsoft visual studio 12.0\vc\include\errno.h" id="107" stamp="1374453976"  exclude="false"/><File path="c:\program files (x86)\microsoft visual studio 12.0\vc\include\share.h" id="108" stamp="1374456134"  exclude="false"/><File path="c:\program files (x86)\microsoft visual studio 12.0\vc\include\memory" id="109" stamp="1374770146"  exclude="false"/><File path="C:\Users\lacti\Desktop\llvm\include\llvm\ADT\StringRef.h" id="10" stamp="1406279562"  exclude="false"/><File path="c:\program files (x86)\microsoft visual studio 12.0\vc\include\string" id="110" stamp="1374456136"  exclude="false"/><File path="C:\Users\lacti\Desktop\llvm\include\llvm\ADT\Twine.h" id="11" stamp="1406279562"  exclude="false"/><File path="C:\Users\lacti\Desktop\llvm\include\llvm\Support\ErrorHandling.h" id="111" stamp="1406279565"  exclude="false"/><File path="C:\Users\lacti\Desktop\llvm\include\llvm\Config\config.h" id="112" stamp="1406282460"  exclude="false"/><File path="C:\Users\lacti\Desktop\llvm\lib\Support\Windows\Signals.inc" id="2" stamp="1406279336"  added="C:\Users\lacti\Desktop\llvm\CppDependOut/Incremental/32038F909F9A62D6CD177418ADC147CFC7916DDA/Includes\ff93398adc39e320f514e8a2834a6f01.xml" exclude="false"/><File path="C:\Users\lacti\Desktop\llvm\include\llvm\Support\FileSystem.h" id="17" stamp="1406279565"  exclude="false"/><File path="C:\Users\lacti\Desktop\llvm\include\llvm\ADT\IntrusiveRefCntPtr.h" id="113" stamp="1406279562"  exclude="false"/><File path="C:\Users\lacti\Desktop\llvm\include\llvm\Support\Casting.h" id="114" stamp="1406279565"  exclude="false"/><File path="c:\program files (x86)\microsoft visual studio 12.0\vc\include\atomic" id="115" stamp="1374770146"  exclude="false"/><File path="c:\program files (x86)\microsoft visual studio 12.0\vc\include\xatomic.h" id="116" stamp="1374456138"  exclude="false"/><File path="c:\program files (x86)\microsoft visual studio 12.0\vc\include\xxatomic" id="117" stamp="1374770146"  exclude="false"/><File path="C:\Users\lacti\Desktop\llvm\include\llvm\Support\TimeValue.h" id="118" stamp="1406279565"  exclude="false"/><File path="c:\program files (x86)\microsoft visual studio 12.0\vc\include\ctime" id="119" stamp="1374456136"  exclude="false"/><File path="c:\program files (x86)\microsoft visual studio 12.0\vc\include\time.h" id="120" stamp="1374453976"  exclude="false"/><File path="c:\program files (x86)\microsoft visual studio 12.0\vc\include\time.inl" id="121" stamp="1374453976"  exclude="false"/><File path="c:\program files (x86)\microsoft visual studio 12.0\vc\include\stack" id="122" stamp="1374456136"  exclude="false"/><File path="c:\program files (x86)\microsoft visual studio 12.0\vc\include\deque" id="123" stamp="1374456136"  exclude="false"/><File path="c:\program files (x86)\microsoft visual studio 12.0\vc\include\tuple" id="124" stamp="1374456138"  exclude="false"/><File path="c:\program files (x86)\microsoft visual studio 12.0\vc\include\vector" id="12" stamp="1374453976"  exclude="false"/><File path="c:\program files (x86)\microsoft visual studio 12.0\vc\include\sys\stat.h" id="125" stamp="1374453976"  exclude="false"/><File path="c:\program files (x86)\microsoft visual studio 12.0\vc\include\sys\stat.inl" id="126" stamp="1374453976"  exclude="false"/><File path="C:\Users\lacti\Desktop\llvm\lib\Support\Windows\WindowsSupport.h" id="127" stamp="1406279336"  exclude="false"/><File path="c:\program files (x86)\windows kits\8.1\include\um\windows.h" id="128" stamp="1377103092"  exclude="false"/><File path="c:\program files (x86)\windows kits\8.1\include\shared\winapifamily.h" id="129" stamp="1371535460"  exclude="false"/><File path="c:\program files (x86)\windows kits\8.1\include\shared\sdkddkver.h" id="130" stamp="1377103056"  exclude="false"/><File path="c:\program files (x86)\microsoft visual studio 12.0\vc\include\excpt.h" id="131" stamp="1374453976"  exclude="false"/><File path="c:\program files (x86)\microsoft visual studio 12.0\vc\include\stdarg.h" id="132" stamp="1374453976"  exclude="false"/><File path="c:\program files (x86)\windows kits\8.1\include\shared\windef.h" id="133" stamp="1377103092"  exclude="false"/><File path="c:\program files (x86)\windows kits\8.1\include\shared\minwindef.h" id="134" stamp="1377102916"  exclude="false"/><File path="c:\program files (x86)\windows kits\8.1\include\shared\specstrings.h" id="135" stamp="1371533312"  exclude="false"/><File path="c:\program files (x86)\windows kits\8.1\include\shared\specstrings_strict.h" id="136" stamp="1371533312"  exclude="false"/><File path="c:\program files (x86)\windows kits\8.1\include\shared\specstrings_undef.h" id="137" stamp="1371533312"  exclude="false"/><File path="c:\program files (x86)\windows kits\8.1\include\shared\driverspecs.h" id="138" stamp="1377102922"  exclude="false"/><File path="c:\program files (x86)\windows kits\8.1\include\shared\sdv_driverspecs.h" id="139" stamp="1371533312"  exclude="false"/><File path="c:\program files (x86)\windows kits\8.1\include\shared\no_sal2.h" id="140" stamp="1377103414"  exclude="false"/><File path="c:\program files (x86)\windows kits\8.1\include\um\winnt.h" id="6" stamp="1377102920"  exclude="false"/><File path="c:\program files (x86)\windows kits\8.1\include\shared\kernelspecs.h" id="141" stamp="1371533306"  exclude="false"/><File path="c:\program files (x86)\windows kits\8.1\include\shared\basetsd.h" id="142" stamp="1371533304"  exclude="false"/><File path="c:\program files (x86)\windows kits\8.1\include\shared\guiddef.h" id="143" stamp="1371533306"  exclude="false"/><File path="c:\program files (x86)\windows kits\8.1\include\shared\pshpack4.h" id="144" stamp="1371533312"  exclude="false"/><File path="c:\program files (x86)\windows kits\8.1\include\shared\poppack.h" id="145" stamp="1371533312"  exclude="false"/><File path="c:\program files (x86)\windows kits\8.1\include\shared\pshpack2.h" id="146" stamp="1371533312"  exclude="false"/><File path="c:\program files (x86)\windows kits\8.1\include\shared\pshpack8.h" id="147" stamp="1371533312"  exclude="false"/><File path="c:\program files (x86)\windows kits\8.1\include\shared\apiset.h" id="148" stamp="1371532642"  exclude="false"/><File path="c:\program files (x86)\windows kits\8.1\include\shared\ktmtypes.h" id="149" stamp="1371535456"  exclude="false"/><File path="c:\program files (x86)\windows kits\8.1\include\um\winbase.h" id="150" stamp="1377102920"  exclude="false"/><File path="c:\program files (x86)\windows kits\8.1\include\shared\apisetcconv.h" id="151" stamp="1371533304"  exclude="false"/><File path="c:\program files (x86)\windows kits\8.1\include\um\minwinbase.h" id="152" stamp="1377102916"  exclude="false"/><File path="c:\program files (x86)\windows kits\8.1\include\um\processenv.h" id="153" stamp="1377102912"  exclude="false"/><File path="c:\program files (x86)\windows kits\8.1\include\um\fileapi.h" id="154" stamp="1377102912"  exclude="false"/><File path="c:\program files (x86)\windows kits\8.1\include\um\debugapi.h" id="155" stamp="1377102912"  exclude="false"/><File path="c:\program files (x86)\windows kits\8.1\include\um\utilapiset.h" id="156" stamp="1377102912"  exclude="false"/><File path="c:\program files (x86)\windows kits\8.1\include\um\handleapi.h" id="157" stamp="1377102912"  exclude="false"/><File path="c:\program files (x86)\windows kits\8.1\include\um\errhandlingapi.h" id="18" stamp="1377102912"  exclude="false"/><File path="c:\program files (x86)\windows kits\8.1\include\um\fibersapi.h" id="158" stamp="1377102912"  exclude="false"/><File path="c:\program files (x86)\windows kits\8.1\include\um\namedpipeapi.h" id="159" stamp="1377102912"  exclude="false"/><File path="c:\program files (x86)\windows kits\8.1\include\um\profileapi.h" id="160" stamp="1377102912"  exclude="false"/><File path="c:\program files (x86)\windows kits\8.1\include\um\heapapi.h" id="161" stamp="1377102912"  exclude="false"/><File path="c:\program files (x86)\windows kits\8.1\include\um\ioapiset.h" id="162" stamp="1377102914"  exclude="false"/><File path="c:\program files (x86)\windows kits\8.1\include\um\synchapi.h" id="19" stamp="1377102912"  exclude="false"/><File path="c:\program files (x86)\windows kits\8.1\include\um\interlockedapi.h" id="163" stamp="1377102912"  exclude="false"/><File path="c:\program files (x86)\windows kits\8.1\include\um\processthreadsapi.h" id="20" stamp="1377102912"  exclude="false"/><File path="c:\program files (x86)\windows kits\8.1\include\um\sysinfoapi.h" id="164" stamp="1377102912"  exclude="false"/><File path="c:\program files (x86)\windows kits\8.1\include\um\memoryapi.h" id="165" stamp="1377102912"  exclude="false"/><File path="c:\program files (x86)\windows kits\8.1\include\um\threadpoollegacyapiset.h" id="166" stamp="1377102914"  exclude="false"/><File path="c:\program files (x86)\windows kits\8.1\include\um\threadpoolapiset.h" id="167" stamp="1377102912"  exclude="false"/><File path="c:\program files (x86)\windows kits\8.1\include\um\bemapiset.h" id="168" stamp="1377102910"  exclude="false"/><File path="c:\program files (x86)\windows kits\8.1\include\um\jobapi.h" id="169" stamp="1377102910"  exclude="false"/><File path="c:\program files (x86)\windows kits\8.1\include\um\wow64apiset.h" id="170" stamp="1377102914"  exclude="false"/><File path="c:\program files (x86)\windows kits\8.1\include\um\libloaderapi.h" id="171" stamp="1377102912"  exclude="false"/><File path="c:\program files (x86)\windows kits\8.1\include\um\securitybaseapi.h" id="172" stamp="1377102914"  exclude="false"/><File path="c:\program files (x86)\windows kits\8.1\include\um\namespaceapi.h" id="173" stamp="1377102912"  exclude="false"/><File path="c:\program files (x86)\windows kits\8.1\include\um\systemtopologyapi.h" id="174" stamp="1377102912"  exclude="false"/><File path="c:\program files (x86)\windows kits\8.1\include\um\processtopologyapi.h" id="175" stamp="1377102912"  exclude="false"/><File path="c:\program files (x86)\windows kits\8.1\include\um\securityappcontainer.h" id="176" stamp="1377102910"  exclude="false"/><File path="c:\program files (x86)\windows kits\8.1\include\um\realtimeapiset.h" id="177" stamp="1377102914"  exclude="false"/><File path="c:\program files (x86)\windows kits\8.1\include\shared\winerror.h" id="178" stamp="1377102920"  exclude="false"/><File path="c:\program files (x86)\windows kits\8.1\include\um\timezoneapi.h" id="179" stamp="1377102914"  exclude="false"/><File path="c:\program files (x86)\windows kits\8.1\include\um\wingdi.h" id="180" stamp="1377103094"  exclude="false"/><File path="c:\program files (x86)\windows kits\8.1\include\shared\pshpack1.h" id="181" stamp="1371533312"  exclude="false"/><File path="c:\program files (x86)\windows kits\8.1\include\um\winuser.h" id="182" stamp="1377103094"  exclude="false"/><File path="c:\program files (x86)\windows kits\8.1\include\shared\tvout.h" id="183" stamp="1371534754"  exclude="false"/><File path="c:\program files (x86)\windows kits\8.1\include\um\winnls.h" id="184" stamp="1377102920"  exclude="false"/><File path="c:\program files (x86)\windows kits\8.1\include\um\datetimeapi.h" id="185" stamp="1377102914"  exclude="false"/><File path="c:\program files (x86)\windows kits\8.1\include\um\stringapiset.h" id="186" stamp="1377102914"  exclude="false"/><File path="c:\program files (x86)\windows kits\8.1\include\um\wincon.h" id="187" stamp="1377103092"  exclude="false"/><File path="c:\program files (x86)\windows kits\8.1\include\um\consoleapi.h" id="21" stamp="1377102914"  exclude="false"/><File path="c:\program files (x86)\windows kits\8.1\include\um\winver.h" id="188" stamp="1377103526"  exclude="false"/><File path="c:\program files (x86)\windows kits\8.1\include\um\verrsrc.h" id="189" stamp="1371533314"  exclude="false"/><File path="c:\program files (x86)\windows kits\8.1\include\um\winreg.h" id="190" stamp="1377102914"  exclude="false"/><File path="c:\program files (x86)\windows kits\8.1\include\um\reason.h" id="191" stamp="1371534750"  exclude="false"/><File path="c:\program files (x86)\windows kits\8.1\include\um\winnetwk.h" id="192" stamp="1377102914"  exclude="false"/><File path="c:\program files (x86)\windows kits\8.1\include\shared\wnnc.h" id="193" stamp="1377102910"  exclude="false"/><File path="c:\program files (x86)\windows kits\8.1\include\shared\stralign.h" id="194" stamp="1371535460"  exclude="false"/><File path="c:\program files (x86)\windows kits\8.1\include\um\winsvc.h" id="195" stamp="1377102920"  exclude="false"/><File path="c:\program files (x86)\windows kits\8.1\include\um\mcx.h" id="196" stamp="1371533530"  exclude="false"/><File path="c:\program files (x86)\windows kits\8.1\include\um\imm.h" id="197" stamp="1377103088"  exclude="false"/><File path="c:\program files (x86)\windows kits\8.1\include\um\ime_cmodes.h" id="198" stamp="1371533318"  exclude="false"/><File path="c:\program files (x86)\windows kits\8.1\include\um\wincrypt.h" id="199" stamp="1377102914"  exclude="false"/><File path="c:\program files (x86)\windows kits\8.1\include\shared\bcrypt.h" id="200" stamp="1377102914"  exclude="false"/><File path="c:\program files (x86)\windows kits\8.1\include\um\ncrypt.h" id="201" stamp="1377102940"  exclude="false"/><File path="c:\program files (x86)\windows kits\8.1\include\um\dpapi.h" id="202" stamp="1371532798"  exclude="false"/><File path="c:\program files (x86)\windows kits\8.1\include\um\dbghelp.h" id="13" stamp="1377102910"  exclude="false"/><File path="c:\program files (x86)\windows kits\8.1\include\um\psapi.h" id="203" stamp="1371533300"  exclude="false"/><Lib name="msvcprtd"/><Lib name="psapi.lib"/><Lib name="dbghelp.lib"/></Index>