<Root>
<Comments>
<c f="1" b="1" e="1"/>
<c f="1" b="2" e="2"/>
<c f="1" b="3" e="3"/>
<c f="1" b="4" e="4"/>
<c f="1" b="5" e="5"/>
<c f="1" b="6" e="6"/>
<c f="1" b="7" e="7"/>
<c f="1" b="8" e="8"/>
<c f="1" b="9" e="9"/>
<c f="1" b="10" e="10"/>
<c f="1" b="11" e="11"/>
<c f="1" b="12" e="12"/>
<c f="1" b="14" e="12"/>
<c f="1" b="34" e="34"/>
<c f="1" b="35" e="34"/>
</Comments>
<Macros/>
<Comments>
<c f="2" b="1" e="1"/>
<c f="2" b="2" e="2"/>
<c f="2" b="3" e="3"/>
<c f="2" b="4" e="4"/>
<c f="2" b="5" e="5"/>
<c f="2" b="6" e="6"/>
<c f="2" b="7" e="7"/>
<c f="2" b="8" e="8"/>
<c f="2" b="9" e="9"/>
<c f="2" b="10" e="10"/>
<c f="2" b="11" e="11"/>
<c f="2" b="12" e="12"/>
<c f="2" b="14" e="12"/>
<c f="2" b="35" e="35"/>
<c f="2" b="37" e="35"/>
</Comments>
<Macros/>
<tun>
<ns name="llvm" id="1d73c86cbd6e1f16c2ab41217745a5b8_544dadc8774ac7e8cdf9804c9bca3e1f" file="2" linestart="19" lineend="35" original="">
<cr namespace="llvm" access="none" kind="class" name="StringRef" id="1d73c86cbd6e1f16c2ab41217745a5b8_1025e290e4030296f4991e57e4952f33" file="2" linestart="20" lineend="20" previous="6f9d54688deb2fea7e6a760a21186275_1025e290e4030296f4991e57e4952f33"/>
<cr namespace="llvm" access="none" depth="2" kind="class" name="SparcELFMCAsmInfo" id="1d73c86cbd6e1f16c2ab41217745a5b8_17ca5b46356df20967764730e7e9c743" file="2" linestart="22" lineend="33">
<base access="public">
<rt>
<cr id="f78cfd7ef40477bc4cfcf388a4e09d63_20e78ca3a5bb5c7726ce6d6527fcde59"/>
</rt>
</base>
<cr access="public" kind="class" name="SparcELFMCAsmInfo" id="1d73c86cbd6e1f16c2ab41217745a5b8_23e48eb65eee3f9f4e04dedd167c375e" file="2" linestart="22" lineend="22"/>
<m name="anchor" id="1d73c86cbd6e1f16c2ab41217745a5b8_cf21e61444fb47481166acaf919c8ae3" file="2" linestart="23" lineend="23" access="private" hasbody="true">
<fpt proto="void">
<bt name="void"/>
</fpt>
</m>
<Decl access="public"/>
<c name="SparcELFMCAsmInfo" id="1d73c86cbd6e1f16c2ab41217745a5b8_2682b2bbaca2437c3521c361e62be31a" file="2" linestart="25" lineend="25" explicit="true" access="public" hasbody="true">
<fpt proto="void">
<bt name="void"/>
</fpt>
<p name="TT" proto="llvm::StringRef" access2="none">
<rt>
<cr id="6f9d54688deb2fea7e6a760a21186275_1025e290e4030296f4991e57e4952f33"/>
</rt>
<Stmt>

</Stmt>
</p>
</c>
<m name="getExprForPersonalitySymbol" id="1d73c86cbd6e1f16c2ab41217745a5b8_ca65662f4f817deed2f89011b8892202" file="2" linestart="26" lineend="28" access="public" hasbody="true">
<fpt const="true" proto="const llvm::MCExpr *">
<pt>
<QualType const="true">
<rt>
<cr id="c6c8e579ec4c80fd3bfd5c18c764ca89_0f29b7896b35764a545396257701b0ee"/>
</rt>
</QualType>
</pt>
</fpt>
<p name="Sym" proto="const llvm::MCSymbol *" isPtr="true" isLiteral="true" access2="none">
<pt>
<QualType const="true">
<rt>
<cr id="c86d8a7a7f1ceeae189fc3b3e5b77305_a4b7885e159e2a7bcf4cb7e2efdfe4ea"/>
</rt>
</QualType>
</pt>
<Stmt>

</Stmt>
</p>
<p name="Encoding" proto="unsigned int" isLiteral="true" isPrimitive="true" access2="none">
<bt name="unsigned int"/>
<Stmt>

</Stmt>
</p>
<p name="Streamer" proto="llvm::MCStreamer &amp;" isRef="true" isLiteral="true" access2="none">
<lrf>
<rt>
<cr id="7345c616ef5527975f62b8656367364b_d43ee9d6c82592155c8c2c9057faef5e"/>
</rt>
</lrf>
<Stmt>

</Stmt>
</p>
</m>
<m name="getExprForFDESymbol" id="1d73c86cbd6e1f16c2ab41217745a5b8_330dc40034cf518a5f173d3584eaa459" file="2" linestart="29" lineend="31" access="public" hasbody="true">
<fpt const="true" proto="const llvm::MCExpr *">
<pt>
<QualType const="true">
<rt>
<cr id="c6c8e579ec4c80fd3bfd5c18c764ca89_0f29b7896b35764a545396257701b0ee"/>
</rt>
</QualType>
</pt>
</fpt>
<p name="Sym" proto="const llvm::MCSymbol *" isPtr="true" isLiteral="true" access2="none">
<pt>
<QualType const="true">
<rt>
<cr id="c86d8a7a7f1ceeae189fc3b3e5b77305_a4b7885e159e2a7bcf4cb7e2efdfe4ea"/>
</rt>
</QualType>
</pt>
<Stmt>

</Stmt>
</p>
<p name="Encoding" proto="unsigned int" isLiteral="true" isPrimitive="true" access2="none">
<bt name="unsigned int"/>
<Stmt>

</Stmt>
</p>
<p name="Streamer" proto="llvm::MCStreamer &amp;" isRef="true" isLiteral="true" access2="none">
<lrf>
<rt>
<cr id="7345c616ef5527975f62b8656367364b_d43ee9d6c82592155c8c2c9057faef5e"/>
</rt>
</lrf>
<Stmt>

</Stmt>
</p>
</m>
<m name="operator=" id="1d73c86cbd6e1f16c2ab41217745a5b8_a93566e538c6dcfca57b0d79b8613d31" file="2" linestart="22" implicit="true" operator="true" access="public" inline="true">
<fpt proto="llvm::SparcELFMCAsmInfo &amp;">
<lrf>
<rt>
<cr id="1d73c86cbd6e1f16c2ab41217745a5b8_17ca5b46356df20967764730e7e9c743"/>
</rt>
</lrf>
</fpt>
<p name="" proto="const llvm::SparcELFMCAsmInfo &amp;" isRef="true" isLiteral="true" access2="none">
<lrf>
<QualType const="true">
<rt>
<cr id="1d73c86cbd6e1f16c2ab41217745a5b8_17ca5b46356df20967764730e7e9c743"/>
</rt>
</QualType>
</lrf>
<Stmt>

</Stmt>
</p>
</m>
<d name="~SparcELFMCAsmInfo" id="1d73c86cbd6e1f16c2ab41217745a5b8_68d601244c61ca1381d2613c68ded313" file="2" linestart="22" lineend="22" implicit="true" access="public" inline="true" hasbody="true" isdef="true">
<fpt proto="void">
<bt name="void"/>
<exception_specifiers nothrow="true"/>
</fpt>
<Stmt>
<u lb="22" cb="7"/>

</Stmt>
</d>
<c name="SparcELFMCAsmInfo" id="1d73c86cbd6e1f16c2ab41217745a5b8_f6e2094ff691ebf2502ae3f85d5be8d4" file="2" linestart="22" lineend="22" copyconst="true" implicit="true" access="public" inline="true">
<fpt proto="void">
<bt name="void"/>
</fpt>
<p name="" proto="const llvm::SparcELFMCAsmInfo &amp;" isRef="true" isLiteral="true" access2="none">
<lrf>
<QualType const="true">
<rt>
<cr id="1d73c86cbd6e1f16c2ab41217745a5b8_17ca5b46356df20967764730e7e9c743"/>
</rt>
</QualType>
</lrf>
<Stmt>

</Stmt>
</p>
</c>
</cr>
</ns>
<NamedDecl name="&lt;using-directive&gt;" id="0020f5b612bdaeebe62ed6cc80ab3546_6728b6b0f829183eb7bbd3d3d987c87d" file="1" linestart="19" lineend="19"/>
<m name="anchor" id="0020f5b612bdaeebe62ed6cc80ab3546_cf21e61444fb47481166acaf919c8ae3" file="1" linestart="21" lineend="21" previous="1d73c86cbd6e1f16c2ab41217745a5b8_cf21e61444fb47481166acaf919c8ae3" access="private" hasbody="true" isdef="true">
<fpt proto="void">
<bt name="void"/>
</fpt>
<Stmt>
<u lb="21" cb="34" le="21" ce="36"/>

</Stmt>
</m>
<c name="SparcELFMCAsmInfo" id="0020f5b612bdaeebe62ed6cc80ab3546_2682b2bbaca2437c3521c361e62be31a" file="1" linestart="23" lineend="49" previous="1d73c86cbd6e1f16c2ab41217745a5b8_2682b2bbaca2437c3521c361e62be31a" explicit="true" access="public" hasbody="true" isdef="true">
<fpt proto="void">
<bt name="void"/>
</fpt>
<p name="TT" proto="llvm::StringRef" access2="none">
<rt>
<cr id="6f9d54688deb2fea7e6a760a21186275_1025e290e4030296f4991e57e4952f33"/>
</rt>
<Stmt>

</Stmt>
</p>
<BaseInit>
<n10 lb="23" cb="20">
<typeptr id="f78cfd7ef40477bc4cfcf388a4e09d63_5f71cb8c8b81f9da8ff354f6c0dc0a11"/>
<temp/>
</n10>

</BaseInit>
<Stmt>
<u lb="23" cb="52" le="49" ce="1">
<xop lb="24" cb="3" le="24" ce="20" kind="=">
<mex lb="24" cb="3" kind="lvalue" id="b2b9336dfe6b80bb5834e13979c78f51_78b1277da8dbf980a2097a44eda4b3b3" nm="IsLittleEndian" arrow="1">
<n32 lb="24" cb="3">
<n19 lb="24" cb="3"/>
</n32>
</mex>
<n9 lb="24" cb="20"/>
</xop>
<dst lb="25" cb="3" le="25" ce="23">
<exp pvirg="true"/>
<Var nm="TheTriple" value="true">
<rt>
<cr id="9306b6949f28c3a31f519bc736944721_f187657d74874d999705b05021f1c276"/>
</rt>
<n10 lb="25" cb="10" le="25" ce="22">
<typeptr id="9306b6949f28c3a31f519bc736944721_ba5c37a0b4ce66f6f2f796a9de247fcd"/>
<temp/>
<mte lb="25" cb="20">
<exp pvirg="true"/>
<n32 lb="25" cb="20">
<n10 lb="25" cb="20">
<typeptr id="96ed60b524dd53b8d6b92c178537632e_b98fe74454382f4da0cfd1cb67c1fc92"/>
<temp/>
<n32 lb="25" cb="20">
<drx lb="25" cb="20" kind="lvalue" nm="TT"/>
</n32>
</n10>
</n32>
</mte>
</n10>
</Var>
</dst>
<dst lb="26" cb="3" le="26" ce="55">
<exp pvirg="true"/>
<Var nm="isV9" value="true">
<bt name="bool"/>
<n46 lb="26" cb="15" le="26" ce="54">
<exp pvirg="true"/>
<xop lb="26" cb="16" le="26" ce="47" kind="==">
<n32 lb="26" cb="16" le="26" ce="34">
<mce lb="26" cb="16" le="26" ce="34" nbparm="0" id="9306b6949f28c3a31f519bc736944721_3b63ae82488928e081c762567bfdb992">
<exp pvirg="true"/>
<mex lb="26" cb="16" le="26" ce="26" id="9306b6949f28c3a31f519bc736944721_3b63ae82488928e081c762567bfdb992" nm="getArch" point="1">
<n32 lb="26" cb="16">
<drx lb="26" cb="16" kind="lvalue" nm="TheTriple"/>
</n32>
</mex>
</mce>
</n32>
<n32 lb="26" cb="39" le="26" ce="47">
<drx lb="26" cb="39" le="26" ce="47" id="9306b6949f28c3a31f519bc736944721_1dfa734793b5a7ee51b57725945a0592" nm="sparcv9"/>
</n32>
</xop>
</n46>
</Var>
</dst>
<if lb="28" cb="3" le="30" ce="3">
<n32 lb="28" cb="7">
<drx lb="28" cb="7" kind="lvalue" nm="isV9"/>
</n32>
<u lb="28" cb="13" le="30" ce="3">
<xop lb="29" cb="5" le="29" ce="45" kind="=">
<mex lb="29" cb="5" kind="lvalue" id="b2b9336dfe6b80bb5834e13979c78f51_7956651dbcb73a6035f581fd867b78bd" nm="PointerSize" arrow="1">
<n32 lb="29" cb="5">
<n19 lb="29" cb="5"/>
</n32>
</mex>
<n32 lb="29" cb="19" le="29" ce="45">
<xop lb="29" cb="19" le="29" ce="45" kind="=">
<mex lb="29" cb="19" kind="lvalue" id="b2b9336dfe6b80bb5834e13979c78f51_7774f3a0ea64078210ad7f0f1b05e3f2" nm="CalleeSaveStackSlotSize" arrow="1">
<n32 lb="29" cb="19">
<n19 lb="29" cb="19"/>
</n32>
</mex>
<n32 lb="29" cb="45">
<n45 lb="29" cb="45">
<flit/>
</n45>
</n32>
</xop>
</n32>
</xop>
</u>
</if>
<xop lb="32" cb="3" le="32" ce="25" kind="=">
<mex lb="32" cb="3" kind="lvalue" id="b2b9336dfe6b80bb5834e13979c78f51_9e0e1b59c7c4c00dffda063814672afa" nm="Data16bitsDirective" arrow="1">
<n32 lb="32" cb="3">
<n19 lb="32" cb="3"/>
</n32>
</mex>
<n32 lb="32" cb="25">
<n52 lb="32" cb="25">
<slit/>
</n52>
</n32>
</xop>
<xop lb="33" cb="3" le="33" ce="25" kind="=">
<mex lb="33" cb="3" kind="lvalue" id="b2b9336dfe6b80bb5834e13979c78f51_c9e978392592eb5d6246bd52806e4665" nm="Data32bitsDirective" arrow="1">
<n32 lb="33" cb="3">
<n19 lb="33" cb="3"/>
</n32>
</mex>
<n32 lb="33" cb="25">
<n52 lb="33" cb="25">
<slit/>
</n52>
</n32>
</xop>
<xop lb="35" cb="3" le="35" ce="49" kind="=">
<mex lb="35" cb="3" kind="lvalue" id="b2b9336dfe6b80bb5834e13979c78f51_279960106ee92fb84779d3b4090f5fe8" nm="Data64bitsDirective" arrow="1">
<n32 lb="35" cb="3">
<n19 lb="35" cb="3"/>
</n32>
</mex>
<co lb="35" cb="25" le="35" ce="49">
<exp pvirg="true"/>
<n32 lb="35" cb="25" le="35" ce="30">
<n46 lb="35" cb="25" le="35" ce="30">
<exp pvirg="true"/>
<drx lb="35" cb="26" kind="lvalue" nm="isV9"/>
</n46>
</n32>
<n32 lb="35" cb="34">
<n52 lb="35" cb="34">
<slit/>
</n52>
</n32>
<n32 lb="35" cb="49">
<n16 lb="35" cb="49">
<exp pvirg="true"/>
</n16>
</n32>
</co>
</xop>
<xop lb="36" cb="3" le="36" ce="19" kind="=">
<mex lb="36" cb="3" kind="lvalue" id="b2b9336dfe6b80bb5834e13979c78f51_14f21e35838dd3b443c2e49b496a339a" nm="ZeroDirective" arrow="1">
<n32 lb="36" cb="3">
<n19 lb="36" cb="3"/>
</n32>
</mex>
<n32 lb="36" cb="19">
<n52 lb="36" cb="19">
<slit/>
</n52>
</n32>
</xop>
<xop lb="37" cb="3" le="37" ce="19" kind="=">
<mex lb="37" cb="3" kind="lvalue" id="b2b9336dfe6b80bb5834e13979c78f51_b454cd304af0749db1b733b37d4ac810" nm="CommentString" arrow="1">
<n32 lb="37" cb="3">
<n19 lb="37" cb="3"/>
</n32>
</mex>
<n32 lb="37" cb="19">
<n52 lb="37" cb="19">
<slit/>
</n52>
</n32>
</xop>
<xop lb="38" cb="3" le="38" ce="15" kind="=">
<mex lb="38" cb="3" kind="lvalue" id="b2b9336dfe6b80bb5834e13979c78f51_432897b0b58ccfd436d9b9f643603816" nm="HasLEB128" arrow="1">
<n32 lb="38" cb="3">
<n19 lb="38" cb="3"/>
</n32>
</mex>
<n9 lb="38" cb="15"/>
</xop>
<xop lb="39" cb="3" le="39" ce="30" kind="=">
<mex lb="39" cb="3" kind="lvalue" id="b2b9336dfe6b80bb5834e13979c78f51_24214ea1a4cb5231c62301e0949b0ba1" nm="SupportsDebugInformation" arrow="1">
<n32 lb="39" cb="3">
<n19 lb="39" cb="3"/>
</n32>
</mex>
<n9 lb="39" cb="30"/>
</xop>
<xop lb="41" cb="3" le="41" ce="39" kind="=">
<mex lb="41" cb="3" kind="lvalue" id="b2b9336dfe6b80bb5834e13979c78f51_ebc0367d5cda0ae4bff046ab96789dda" nm="ExceptionsType" arrow="1">
<n32 lb="41" cb="3">
<n19 lb="41" cb="3"/>
</n32>
</mex>
<drx lb="41" cb="20" le="41" ce="39" id="b2b9336dfe6b80bb5834e13979c78f51_7304df4a61cc2604ed23cc0b80c4aaf6" nm="DwarfCFI"/>
</xop>
<xop lb="43" cb="3" le="43" ce="36" kind="=">
<mex lb="43" cb="3" kind="lvalue" id="b2b9336dfe6b80bb5834e13979c78f51_f7ad0ac9be2716bb78c61a41035ba58b" nm="SunStyleELFSectionSwitchSyntax" arrow="1">
<n32 lb="43" cb="3">
<n19 lb="43" cb="3"/>
</n32>
</mex>
<n9 lb="43" cb="36"/>
</xop>
<xop lb="44" cb="3" le="44" ce="35" kind="=">
<mex lb="44" cb="3" kind="lvalue" id="b2b9336dfe6b80bb5834e13979c78f51_9fe111f85626d27359428dc6c2727999" nm="UsesELFSectionDirectiveForBSS" arrow="1">
<n32 lb="44" cb="3">
<n19 lb="44" cb="3"/>
</n32>
</mex>
<n9 lb="44" cb="35"/>
</xop>
<if lb="46" cb="3" le="48" ce="30">
<xop lb="46" cb="7" le="47" ce="42" kind="||">
<xop lb="46" cb="7" le="46" ce="42" kind="==">
<n32 lb="46" cb="7" le="46" ce="23">
<mce lb="46" cb="7" le="46" ce="23" nbparm="0" id="9306b6949f28c3a31f519bc736944721_97983d69c24a6df0f0d0b6bb6062f7ab">
<exp pvirg="true"/>
<mex lb="46" cb="7" le="46" ce="17" id="9306b6949f28c3a31f519bc736944721_97983d69c24a6df0f0d0b6bb6062f7ab" nm="getOS" point="1">
<n32 lb="46" cb="7">
<drx lb="46" cb="7" kind="lvalue" nm="TheTriple"/>
</n32>
</mex>
</mce>
</n32>
<n32 lb="46" cb="28" le="46" ce="42">
<drx lb="46" cb="28" le="46" ce="42" id="9306b6949f28c3a31f519bc736944721_86dce1a320901508d18f1a4517f98137" nm="Solaris"/>
</n32>
</xop>
<xop lb="47" cb="7" le="47" ce="42" kind="==">
<n32 lb="47" cb="7" le="47" ce="23">
<mce lb="47" cb="7" le="47" ce="23" nbparm="0" id="9306b6949f28c3a31f519bc736944721_97983d69c24a6df0f0d0b6bb6062f7ab">
<exp pvirg="true"/>
<mex lb="47" cb="7" le="47" ce="17" id="9306b6949f28c3a31f519bc736944721_97983d69c24a6df0f0d0b6bb6062f7ab" nm="getOS" point="1">
<n32 lb="47" cb="7">
<drx lb="47" cb="7" kind="lvalue" nm="TheTriple"/>
</n32>
</mex>
</mce>
</n32>
<n32 lb="47" cb="28" le="47" ce="42">
<drx lb="47" cb="28" le="47" ce="42" id="9306b6949f28c3a31f519bc736944721_840afd700a237527f4c44a85dc3aa584" nm="OpenBSD"/>
</n32>
</xop>
</xop>
<xop lb="48" cb="5" le="48" ce="30" kind="=">
<mex lb="48" cb="5" kind="lvalue" id="b2b9336dfe6b80bb5834e13979c78f51_d478bf880f15b54cf6645ffbfcdd8e4b" nm="UseIntegratedAssembler" arrow="1">
<n32 lb="48" cb="5">
<n19 lb="48" cb="5"/>
</n32>
</mex>
<n9 lb="48" cb="30"/>
</xop>
</if>
</u>

</Stmt>
</c>
<m name="getExprForPersonalitySymbol" id="0020f5b612bdaeebe62ed6cc80ab3546_ca65662f4f817deed2f89011b8892202" file="1" linestart="51" lineend="62" previous="1d73c86cbd6e1f16c2ab41217745a5b8_ca65662f4f817deed2f89011b8892202" access="public" hasbody="true" isdef="true">
<fpt const="true" proto="const llvm::MCExpr *">
<pt>
<QualType const="true">
<rt>
<cr id="c6c8e579ec4c80fd3bfd5c18c764ca89_0f29b7896b35764a545396257701b0ee"/>
</rt>
</QualType>
</pt>
</fpt>
<p name="Sym" proto="const llvm::MCSymbol *" isPtr="true" isLiteral="true" access2="none">
<pt>
<QualType const="true">
<rt>
<cr id="c86d8a7a7f1ceeae189fc3b3e5b77305_a4b7885e159e2a7bcf4cb7e2efdfe4ea"/>
</rt>
</QualType>
</pt>
<Stmt>

</Stmt>
</p>
<p name="Encoding" proto="unsigned int" isLiteral="true" isPrimitive="true" access2="none">
<bt name="unsigned int"/>
<Stmt>

</Stmt>
</p>
<p name="Streamer" proto="llvm::MCStreamer &amp;" isRef="true" isLiteral="true" access2="none">
<lrf>
<rt>
<cr id="7345c616ef5527975f62b8656367364b_d43ee9d6c82592155c8c2c9057faef5e"/>
</rt>
</lrf>
<Stmt>

</Stmt>
</p>
<Stmt>
<u lb="54" cb="76" le="62" ce="1">
<if lb="55" cb="3" le="59" ce="3">
<n32 lb="55" cb="7" le="55" ce="25">
<xop lb="55" cb="7" le="55" ce="25" kind="&amp;">
<n32 lb="55" cb="7">
<drx lb="55" cb="7" kind="lvalue" nm="Encoding"/>
</n32>
<n32 lb="55" cb="18" le="55" ce="25">
<drx lb="55" cb="18" le="55" ce="25" id="b9ebd51a2a93cddba506c28533a60962_2842319b0123578bbabbfa014f06e697" nm="DW_EH_PE_pcrel"/>
</n32>
</xop>
</n32>
<u lb="55" cb="41" le="59" ce="3">
<dst lb="56" cb="5" le="56" ce="43">
<exp pvirg="true"/>
<Var nm="Ctx">
<lrf>
<rt>
<cr id="c86d8a7a7f1ceeae189fc3b3e5b77305_66d5a04d181dc2d379aee3c1da9a8316"/>
</rt>
</lrf>
<mce lb="56" cb="22" le="56" ce="42" nbparm="0" id="7345c616ef5527975f62b8656367364b_1ebd9bff775643206ab055b6db9f0a00">
<exp pvirg="true"/>
<mex lb="56" cb="22" le="56" ce="31" id="7345c616ef5527975f62b8656367364b_1ebd9bff775643206ab055b6db9f0a00" nm="getContext" point="1">
<n32 lb="56" cb="22">
<drx lb="56" cb="22" kind="lvalue" nm="Streamer"/>
</n32>
</mex>
</mce>
</Var>
</dst>
<rx lb="57" cb="5" le="58" ce="70" pvirg="true">
<n32 lb="57" cb="12" le="58" ce="70">
<ce lb="57" cb="12" le="58" ce="70" nbparm="3" id="1eba798e03a5e1ca9461d342da463727_3deeb4fc850738c84467802acede5f1a">
<exp pvirg="true"/>
<n32 lb="57" cb="12" le="57" ce="25">
<drx lb="57" cb="12" le="57" ce="25" kind="lvalue" id="1eba798e03a5e1ca9461d342da463727_3deeb4fc850738c84467802acede5f1a" nm="Create"/>
</n32>
<drx lb="57" cb="32" le="57" ce="45" id="1eba798e03a5e1ca9461d342da463727_60a708cab7cfc385f018675f67ba9f67" nm="VK_Sparc_R_DISP32"/>
<n32 lb="58" cb="32" le="58" ce="64">
<ce lb="58" cb="32" le="58" ce="64" nbparm="2" id="c6c8e579ec4c80fd3bfd5c18c764ca89_40a0185f09695e398e07eeb7593516da">
<exp pvirg="true"/>
<n32 lb="58" cb="32" le="58" ce="49">
<drx lb="58" cb="32" le="58" ce="49" kind="lvalue" id="c6c8e579ec4c80fd3bfd5c18c764ca89_40a0185f09695e398e07eeb7593516da" nm="Create"/>
</n32>
<n32 lb="58" cb="56">
<drx lb="58" cb="56" kind="lvalue" nm="Sym"/>
</n32>
<drx lb="58" cb="61" kind="lvalue" nm="Ctx"/>
</ce>
</n32>
<drx lb="58" cb="67" kind="lvalue" nm="Ctx"/>
</ce>
</n32>
</rx>
</u>
</if>
<rx lb="61" cb="3" le="61" ce="72" pvirg="true">
<mce lb="61" cb="10" le="61" ce="72" nbparm="3" id="b2b9336dfe6b80bb5834e13979c78f51_06bc75dc3a5491be135b469a348c0852">
<exp pvirg="true"/>
<mex lb="61" cb="10" le="61" ce="21" id="b2b9336dfe6b80bb5834e13979c78f51_06bc75dc3a5491be135b469a348c0852" nm="getExprForPersonalitySymbol" arrow="1">
<n32 lb="61" cb="21">
<n32 lb="61" cb="21">
<n19 lb="61" cb="21"/>
</n32>
</n32>
</mex>
<n32 lb="61" cb="49">
<drx lb="61" cb="49" kind="lvalue" nm="Sym"/>
</n32>
<n32 lb="61" cb="54">
<drx lb="61" cb="54" kind="lvalue" nm="Encoding"/>
</n32>
<drx lb="61" cb="64" kind="lvalue" nm="Streamer"/>
</mce>
</rx>
</u>

</Stmt>
</m>
<m name="getExprForFDESymbol" id="0020f5b612bdaeebe62ed6cc80ab3546_330dc40034cf518a5f173d3584eaa459" file="1" linestart="64" lineend="74" previous="1d73c86cbd6e1f16c2ab41217745a5b8_330dc40034cf518a5f173d3584eaa459" access="public" hasbody="true" isdef="true">
<fpt const="true" proto="const llvm::MCExpr *">
<pt>
<QualType const="true">
<rt>
<cr id="c6c8e579ec4c80fd3bfd5c18c764ca89_0f29b7896b35764a545396257701b0ee"/>
</rt>
</QualType>
</pt>
</fpt>
<p name="Sym" proto="const llvm::MCSymbol *" isPtr="true" isLiteral="true" access2="none">
<pt>
<QualType const="true">
<rt>
<cr id="c86d8a7a7f1ceeae189fc3b3e5b77305_a4b7885e159e2a7bcf4cb7e2efdfe4ea"/>
</rt>
</QualType>
</pt>
<Stmt>

</Stmt>
</p>
<p name="Encoding" proto="unsigned int" isLiteral="true" isPrimitive="true" access2="none">
<bt name="unsigned int"/>
<Stmt>

</Stmt>
</p>
<p name="Streamer" proto="llvm::MCStreamer &amp;" isRef="true" isLiteral="true" access2="none">
<lrf>
<rt>
<cr id="7345c616ef5527975f62b8656367364b_d43ee9d6c82592155c8c2c9057faef5e"/>
</rt>
</lrf>
<Stmt>

</Stmt>
</p>
<Stmt>
<u lb="67" cb="68" le="74" ce="1">
<if lb="68" cb="3" le="72" ce="3">
<n32 lb="68" cb="7" le="68" ce="25">
<xop lb="68" cb="7" le="68" ce="25" kind="&amp;">
<n32 lb="68" cb="7">
<drx lb="68" cb="7" kind="lvalue" nm="Encoding"/>
</n32>
<n32 lb="68" cb="18" le="68" ce="25">
<drx lb="68" cb="18" le="68" ce="25" id="b9ebd51a2a93cddba506c28533a60962_2842319b0123578bbabbfa014f06e697" nm="DW_EH_PE_pcrel"/>
</n32>
</xop>
</n32>
<u lb="68" cb="41" le="72" ce="3">
<dst lb="69" cb="5" le="69" ce="43">
<exp pvirg="true"/>
<Var nm="Ctx">
<lrf>
<rt>
<cr id="c86d8a7a7f1ceeae189fc3b3e5b77305_66d5a04d181dc2d379aee3c1da9a8316"/>
</rt>
</lrf>
<mce lb="69" cb="22" le="69" ce="42" nbparm="0" id="7345c616ef5527975f62b8656367364b_1ebd9bff775643206ab055b6db9f0a00">
<exp pvirg="true"/>
<mex lb="69" cb="22" le="69" ce="31" id="7345c616ef5527975f62b8656367364b_1ebd9bff775643206ab055b6db9f0a00" nm="getContext" point="1">
<n32 lb="69" cb="22">
<drx lb="69" cb="22" kind="lvalue" nm="Streamer"/>
</n32>
</mex>
</mce>
</Var>
</dst>
<rx lb="70" cb="5" le="71" ce="70" pvirg="true">
<n32 lb="70" cb="12" le="71" ce="70">
<ce lb="70" cb="12" le="71" ce="70" nbparm="3" id="1eba798e03a5e1ca9461d342da463727_3deeb4fc850738c84467802acede5f1a">
<exp pvirg="true"/>
<n32 lb="70" cb="12" le="70" ce="25">
<drx lb="70" cb="12" le="70" ce="25" kind="lvalue" id="1eba798e03a5e1ca9461d342da463727_3deeb4fc850738c84467802acede5f1a" nm="Create"/>
</n32>
<drx lb="70" cb="32" le="70" ce="45" id="1eba798e03a5e1ca9461d342da463727_60a708cab7cfc385f018675f67ba9f67" nm="VK_Sparc_R_DISP32"/>
<n32 lb="71" cb="32" le="71" ce="64">
<ce lb="71" cb="32" le="71" ce="64" nbparm="2" id="c6c8e579ec4c80fd3bfd5c18c764ca89_40a0185f09695e398e07eeb7593516da">
<exp pvirg="true"/>
<n32 lb="71" cb="32" le="71" ce="49">
<drx lb="71" cb="32" le="71" ce="49" kind="lvalue" id="c6c8e579ec4c80fd3bfd5c18c764ca89_40a0185f09695e398e07eeb7593516da" nm="Create"/>
</n32>
<n32 lb="71" cb="56">
<drx lb="71" cb="56" kind="lvalue" nm="Sym"/>
</n32>
<drx lb="71" cb="61" kind="lvalue" nm="Ctx"/>
</ce>
</n32>
<drx lb="71" cb="67" kind="lvalue" nm="Ctx"/>
</ce>
</n32>
</rx>
</u>
</if>
<rx lb="73" cb="3" le="73" ce="64" pvirg="true">
<mce lb="73" cb="10" le="73" ce="64" nbparm="3" id="b2b9336dfe6b80bb5834e13979c78f51_8fea47196e7c7db9d674c644f63bba47">
<exp pvirg="true"/>
<mex lb="73" cb="10" le="73" ce="21" id="b2b9336dfe6b80bb5834e13979c78f51_8fea47196e7c7db9d674c644f63bba47" nm="getExprForFDESymbol" arrow="1">
<n32 lb="73" cb="21">
<n32 lb="73" cb="21">
<n19 lb="73" cb="21"/>
</n32>
</n32>
</mex>
<n32 lb="73" cb="41">
<drx lb="73" cb="41" kind="lvalue" nm="Sym"/>
</n32>
<n32 lb="73" cb="46">
<drx lb="73" cb="46" kind="lvalue" nm="Encoding"/>
</n32>
<drx lb="73" cb="56" kind="lvalue" nm="Streamer"/>
</mce>
</rx>
</u>

</Stmt>
</m>
</tun>
</Root>
